{
  "scraped_at": "2026-06-18T04:48:50.751229",
  "date": "2026-06-18",
  "total_articles": 33,
  "sources": [
    "KathmanduPost",
    "NagarikNews",
    "News24"
  ],
  "articles": [
    {
      "title": "नी शक्तिपीठदेखि विकाससम्म : सप्तरीको हनुमाननगरमा मेयरको प्रतिबद्धता र जनताको आक्रोश",
      "summary": "नी शक्तिपीठदेखि विकाससम्म : सप्तरीको हनुमाननगरमा मेयरको प्रतिबद्धता र जनताको आक्रोश",
      "source": "News24",
      "language": "np",
      "source_url": "https://www.news24nepal.com/detail/13165",
      "image_url": "https://www.news24nepal.com/uploads/posts/400X300/Sidha-Kura-Meyor-sanga-1781668751.jpg"
    },
    {
      "title": "पिपरा गाउँपालिका लक्ष्य । पूर्वाधारदेखि डिजिटल सेवा सुधारसम्म",
      "summary": "पिपरा गाउँपालिका लक्ष्य । पूर्वाधारदेखि डिजिटल सेवा सुधारसम्म",
      "source": "News24",
      "language": "np",
      "source_url": "https://www.news24nepal.com/detail/13155",
      "image_url": "https://www.news24nepal.com/uploads/posts/400X300/Sidha-Kura-Meyor-sanga-1781496320.jpg"
    },
    {
      "title": "घोटाला काण्डः ठूला उद्योगपति एउटै फाइलमा, कोको परे फन्दामा ?",
      "summary": "घोटाला काण्डः ठूला उद्योगपति एउटै फाइलमा, कोको परे फन्दामा ?",
      "source": "News24",
      "language": "np",
      "source_url": "https://www.news24nepal.com/detail/13152",
      "image_url": "https://www.news24nepal.com/uploads/posts/400X300/arbau-1781495564.jpg"
    },
    {
      "title": "त ब्याच बाहेक अन्य करेन्ट चाउचाउ खान योग्य रहेको यशोधा फुड्सको भनाइ",
      "summary": "त ब्याच बाहेक अन्य करेन्ट चाउचाउ खान योग्य रहेको यशोधा फुड्सको भनाइ",
      "source": "News24",
      "language": "np",
      "source_url": "https://www.news24nepal.com/detail/13148",
      "image_url": "https://www.news24nepal.com/uploads/posts/400X300/01-1781430771.png"
    },
    {
      "title": "नेपाल मोबिलिटी एक्स्पो २०२६ को स्टल बाँडफाँड कार्यक्रम सम्पन्न",
      "summary": "नेपाल मोबिलिटी एक्स्पो २०२६ को स्टल बाँडफाँड कार्यक्रम सम्पन्न",
      "source": "News24",
      "language": "np",
      "source_url": "https://www.news24nepal.com/detail/13145",
      "image_url": "https://www.news24nepal.com/uploads/posts/400X300/DSC07982-1781429649.jpg"
    },
    {
      "title": "त्तम मासमा शिवालय महादेव मन्दिरमा धार्मिक जागरण : दुईदिने भजन–कीर्तन तथा कथा वाचन भव्य रूपमा सम्पन्न",
      "summary": "त्तम मासमा शिवालय महादेव मन्दिरमा धार्मिक जागरण : दुईदिने भजन–कीर्तन तथा कथा वाचन भव्य रूपमा सम्पन्न",
      "source": "News24",
      "language": "np",
      "source_url": "https://www.news24nepal.com/detail/13144",
      "image_url": "https://www.news24nepal.com/uploads/posts/400X300/2-1781420014.jpg"
    },
    {
      "title": "भाडादेखि विद्युत र पानीको महशुलसमेत बुझाउँदैनन् उद्योगीहरु",
      "summary": "भाडादेखि विद्युत र पानीको महशुलसमेत बुझाउँदैनन् उद्योगीहरु",
      "source": "News24",
      "language": "np",
      "source_url": "https://www.news24nepal.com/detail/13143",
      "image_url": "https://www.news24nepal.com/uploads/posts/400X300/udhyug-1781409340.jpg"
    },
    {
      "title": "्षार्थी चिकित्सकमाथि श्रम शोषण, एप्रोन लगाएरै सडकमा उत्रिए",
      "summary": "्षार्थी चिकित्सकमाथि श्रम शोषण, एप्रोन लगाएरै सडकमा उत्रिए",
      "source": "News24",
      "language": "np",
      "source_url": "https://www.news24nepal.com/detail/13139",
      "image_url": "https://www.news24nepal.com/uploads/posts/400X300/chikitshak-aandolit-1781407995.jpg"
    },
    {
      "title": "ै पहिलो बर्ड कार्यक्रम शुभारम्भ",
      "summary": "ै पहिलो बर्ड कार्यक्रम शुभारम्भ",
      "source": "News24",
      "language": "np",
      "source_url": "https://www.news24nepal.com/detail/13138",
      "image_url": "https://www.news24nepal.com/uploads/posts/400X300/ktm-1781332907.jpg"
    },
    {
      "title": "ता बाधा होइन अवसरः आत्मनिर्भर बन्दै सिन्धुपाल्चोकका १३६ जना",
      "summary": "ता बाधा होइन अवसरः आत्मनिर्भर बन्दै सिन्धुपाल्चोकका १३६ जना",
      "source": "News24",
      "language": "np",
      "source_url": "https://www.news24nepal.com/detail/13137",
      "image_url": "https://www.news24nepal.com/uploads/posts/400X300/Utpadan-Ra-Aatmanirbharta-1781319291.jpg"
    },
    {
      "title": "र्ष पुरानो बौद्ध ग्रन्थ जोगाउने अद्भुत परम्परा",
      "summary": "र्ष पुरानो बौद्ध ग्रन्थ जोगाउने अद्भुत परम्परा",
      "source": "News24",
      "language": "np",
      "source_url": "https://www.news24nepal.com/detail/13136",
      "image_url": "https://www.news24nepal.com/uploads/posts/400X300/Pragya-Paramita-1781319071.jpg"
    },
    {
      "title": "कै चासोमा हेटौडा, बसाई सर्नेको भीड बर्सेनि उच्च",
      "summary": "कै चासोमा हेटौडा, बसाई सर्नेको भीड बर्सेनि उच्च",
      "source": "News24",
      "language": "np",
      "source_url": "https://www.news24nepal.com/detail/13132",
      "image_url": "https://www.news24nepal.com/uploads/posts/400X300/Basaisaraiko-Rojai-Hetauda-1781317883.jpg"
    },
    {
      "title": "Domestic violence is on the rise. Nepal sees 528 spousal deaths in six years",
      "summary": "Police data show 68 women were killed by husbands in FY 2025–26 alone. Experts cite relationship stress, mistrust and weak intervention systems as key drivers.",
      "source": "KathmanduPost",
      "language": "en",
      "source_url": "https://kathmandupost.com/national/2026/06/18/domestic-violence-is-on-the-rise-nepal-sees-528-spousal-deaths-in-six-years",
      "image_url": "https://assets-api.kathmandupost.com/thumb.php?src=https://assets-cdn.kathmandupost.com/uploads/source/news/2019/third-party/voilenceagainstwomen-1781747829.jpg&w=300&height=200"
    },
    {
      "title": "Sudurpaschim has seen huge investment in sports infrastructure but has little to show for it",
      "summary": "Political favouritism and poor planning have rendered a multibillion-rupee investment in sports infrastructure virtually useless across Sudurpaschim.",
      "source": "KathmanduPost",
      "language": "en",
      "source_url": "https://kathmandupost.com/national/2026/06/18/sudurpaschim-has-seen-huge-investment-in-sports-infrastructure-but-has-little-to-show-for-it",
      "image_url": "https://assets-api.kathmandupost.com/thumb.php?src=https://assets-cdn.kathmandupost.com/uploads/source/news/2026/news/darchula317620260254031000x0-1781748956.jpg&w=300&height=200"
    },
    {
      "title": "Passport procurement under scrutiny as antigraft body arrests four",
      "summary": "Arrests made and investigations widened amid concerns over failed data migration, tender issues, and dwindling passport stocks.",
      "source": "KathmanduPost",
      "language": "en",
      "source_url": "https://kathmandupost.com/national/2026/06/18/passport-procurement-under-scrutiny-as-antigraft-body-arrests-four",
      "image_url": "https://assets-api.kathmandupost.com/thumb.php?src=https://assets-cdn.kathmandupost.com/uploads/source/news/2026/news/passportdepartment0812023021025261120241234301000x0-1781746867.jpg&w=300&height=200"
    },
    {
      "title": "15 ministers, 15 years later, Nepal’s aviation overhaul remains grounded",
      "summary": "With the European Union maintaining its flight ban on Nepali airlines in its latest safety list, the new government faces pressure to bifurcate CAAN and deliver aviation reform.",
      "source": "KathmanduPost",
      "language": "en",
      "source_url": "https://kathmandupost.com/money/2026/06/17/15-ministers-15-years-later-nepal-s-aviation-overhaul-remains-grounded",
      "image_url": "https://assets-api.kathmandupost.com/thumb.php?src=https://assets-cdn.kathmandupost.com/uploads/source/news/2026/third-party/Untitled1-1781707577.jpg&w=600&height=400"
    },
    {
      "title": "Early controversies cloud Speaker Aryal’s tenure",
      "summary": "With the European Union maintaining its flight ban on Nepali airlines in its latest safety list, the new government faces pressure to bifurcate CAAN and deliver aviation reform.",
      "source": "KathmanduPost",
      "language": "en",
      "source_url": "https://kathmandupost.com/editorial/2026/06/17/early-controversies-cloud-speaker-aryal-s-tenure",
      "image_url": "https://assets-api.kathmandupost.com/thumb.php?src=https://assets-cdn.kathmandupost.com/uploads/source/news/2026/third-party/MileeAishwarya-1781750333.jpg&w=400&height=267"
    },
    {
      "title": "The bartering of BP’s soul",
      "summary": "While the opposition has stretched its protests, the Speaker’s handling of recent disputes has done little to ease the growing trust deficit.",
      "source": "KathmanduPost",
      "language": "en",
      "source_url": "https://kathmandupost.com/columns/2026/06/17/the-bartering-of-bp-s-soul",
      "image_url": "https://assets-api.kathmandupost.com/thumb.php?src=https://assets-cdn.kathmandupost.com/uploads/source/news/2026/third-party/Fitness-1781749868.jpg&w=400&height=267"
    },
    {
      "title": "The race for influence in South Asia",
      "summary": "To restore the party to its historic glory, Gagan Thapa’s mission cannot be just organisational; it must also be existential.",
      "source": "KathmanduPost",
      "language": "en",
      "source_url": "https://kathmandupost.com/columns/2026/06/17/the-race-for-influence-in-south-asia",
      "image_url": "https://assets-api.kathmandupost.com/thumb.php?src=https://assets-cdn.kathmandupost.com/uploads/source/news/2026/third-party/BhuvanNagarkoti-1781749385.jpg&w=400&height=267"
    },
    {
      "title": "Right budget for the moment. Now Nepal must make it fly",
      "summary": "While the US is not yet a major player in the region’s infrastructure development, China is poised to become one despite debt concerns.",
      "source": "KathmanduPost",
      "language": "en",
      "source_url": "https://kathmandupost.com/columns/2026/06/17/right-budget-for-the-moment-now-nepal-must-make-it-fly",
      "image_url": "https://assets-api.kathmandupost.com/thumb.php?src=https://assets-cdn.kathmandupost.com/uploads/source/news/2026/news/darchula317620260254031000x0-1781748956.jpg&w=400&height=267"
    },
    {
      "title": "When burnout hits, move—but don’t push harder",
      "summary": "Twelve months from now, the measure of this budget will not be what was announced, but what changed.",
      "source": "KathmanduPost",
      "language": "en",
      "source_url": "https://kathmandupost.com/art-culture/2026/06/18/when-burnout-hits-move-but-don-t-push-harder",
      "image_url": "https://assets-api.kathmandupost.com/thumb.php?src=https://assets-cdn.kathmandupost.com/uploads/source/news/2019/third-party/voilenceagainstwomen-1781747829.jpg&w=400&height=267"
    },
    {
      "title": "Movie review: Finding love after trauma in ‘The World of Love’",
      "summary": "After working with writers like Arundhati Roy and Sudha Murty, Milee Aishwarya reflects on what makes a good book and why readers still matter.",
      "source": "KathmanduPost",
      "language": "en",
      "source_url": "https://kathmandupost.com/art-culture/2026/06/17/finding-love-after-trauma-in-the-world-of-love",
      "image_url": "https://assets-api.kathmandupost.com/thumb.php?src=https://assets-cdn.kathmandupost.com/uploads/source/news/2026/third-party/RastriyaSwatantraParty-1781747412.jpg&w=400&height=267"
    },
    {
      "title": "Everyday AI: Aneel Neupane",
      "summary": "In a culture that celebrates exhaustion, consistent mobility can support both physical and mental well-being.",
      "source": "KathmanduPost",
      "language": "en",
      "source_url": "https://kathmandupost.com/art-culture/2026/06/17/everyday-ai-aneel-neupane",
      "image_url": "https://assets-api.kathmandupost.com/thumb.php?src=https://assets-cdn.kathmandupost.com/uploads/source/news/2026/news/passportdepartment0812023021025261120241234301000x0-1781746867.jpg&w=400&height=267"
    },
    {
      "title": "What our relationships with AI reveal about modern loneliness",
      "summary": "Bhuvan Nagarkoti shot a 4-under 68 to retain a two-stroke lead over top amateur Sadbhav Acharya after the second round of the Surya Nepal Premier Golf Championship at Gokarna Golf Club.",
      "source": "KathmanduPost",
      "language": "en",
      "source_url": "https://kathmandupost.com/art-culture/2026/06/16/what-our-relationships-with-ai-reveal-about-modern-loneliness",
      "image_url": "https://assets-api.kathmandupost.com/thumb.php?src=https://assets-cdn.kathmandupost.com/uploads/source/news/2026/third-party/Untitled1-1781707577.jpg&w=400&height=267"
    },
    {
      "title": "Nepalis making treacherous trip to Europe through the Balkan route",
      "summary": "Political favouritism and poor planning have rendered a multibillion-rupee investment in sports infrastructure virtually useless across Sudurpaschim.",
      "source": "KathmanduPost",
      "language": "en",
      "source_url": "https://kathmandupost.com/nepali-diaspora/2026/06/06/nepalis-europe-odyssey-through-the-treacherous-balkan-route",
      "image_url": "https://assets-api.kathmandupost.com/thumb.php?src=https://assets-cdn.kathmandupost.com/uploads/source/news/2026/third-party/whatsappimage20260616at18382616620260306491000x0-1781705813.jpg&w=400&height=267"
    },
    {
      "title": "Roshan Adhikari of Centerlight refutes Daily Wire’s claims of Medicaid fraud",
      "summary": "Police data show 68 women were killed by husbands in FY 2025–26 alone. Experts cite relationship stress, mistrust and weak intervention systems as key drivers.",
      "source": "KathmanduPost",
      "language": "en",
      "source_url": "https://kathmandupost.com/nepali-diaspora/2026/06/06/roshan-adhikari-of-centerlight-refutes-daily-wire-s-claims-of-medicaid-fraud",
      "image_url": "https://assets-api.kathmandupost.com/thumb.php?src=https://assets-cdn.kathmandupost.com/uploads/source/news/2026/third-party/apaharan17620260212521000x0-1781703667.jpg&w=400&height=267"
    },
    {
      "title": "How did Nepali and Bhutanese communities get involved in a Medicaid scandal in the US?",
      "summary": "The party’s first general convention is set to endorse ‘constitutional socialism’, ban nepotism and expand the central committee to 136 members.",
      "source": "KathmanduPost",
      "language": "en",
      "source_url": "https://kathmandupost.com/nepali-diaspora/2026/06/04/how-did-nepali-and-bhutanese-communities-get-involved-in-a-medicaid-scandal-in-the-us",
      "image_url": "https://assets-api.kathmandupost.com/thumb.php?src=https://assets-cdn.kathmandupost.com/uploads/source/news/2026/third-party/thumb4-1781701802.jpg&w=400&height=267"
    },
    {
      "title": "Cambodia waives overstay fines for 602 Nepalis",
      "summary": "Arrests made and investigations widened amid concerns over failed data migration, tender issues, and dwindling passport stocks.",
      "source": "KathmanduPost",
      "language": "en",
      "source_url": "https://kathmandupost.com/nepali-diaspora/2026/05/29/cambodia-waives-overstay-fines-for-602-nepalis",
      "image_url": "https://assets-api.kathmandupost.com/thumb.php?src=https://assets-cdn.kathmandupost.com/uploads/source/news/2026/world/H3C72CWDQVOQXB4DIIQOJBCWQU-1781690926.jpg&w=400&height=267"
    },
    {
      "title": "राप्रपाको कार्यसम्पादन समिति बैठक बस्दै",
      "summary": "राष्ट्रिय प्रजातन्त्र पार्टी (राप्रपा)को केन्द्रीय कार्यसम्पादन समितिको बैठक आज (बिहीबार) बस्दै छ।",
      "source": "NagarikNews",
      "language": "np",
      "source_url": "https://nagariknews.nagariknetwork.com/politics/rpp-s-performance-committee-meeting-underway-85-42.html?click_from=just_in",
      "image_url": "https://images.nagariknewscdn.com/thumbs/2025/third-party/1775970449_rpp-480x320.jpg"
    },
    {
      "title": "प्रतिनिधिसभा बैठक बस्दै : आज पनि बजेटमाथि छलफल, मन्त्रीहरूले जवाफ दिने",
      "summary": "जिल्लामा पछिल्लो महिनामा भएका सवारी दुर्घटनाहरूमा मानवीय त्रुटि र चालकको लापर्वाही नै मुख्य कारक रहेको पाइएको छ।",
      "source": "NagarikNews",
      "language": "np",
      "source_url": "https://nagariknews.nagariknetwork.com/social-affairs/road-accident-graph-rises-in-jhapa-br-66-26.html?click_from=just_in",
      "image_url": "https://images.nagariknewscdn.com/thumbs/2026/third-party/1771124570_1764911820_1649837678_accident-1200x560-1200x560 (1)-480x320.jpg"
    },
    {
      "title": "रास्वपा प्रथम महाधिवेशन : महाधिवेशन स्थल निर्माण तीव्र",
      "summary": "संयुक्त राज्य अमेरिका र इरानले युद्ध अन्त्य गर्न डिजाइन गरिएको समझदारी पत्र (एमओयू) मा हस्ताक्षर गरेका छन्।",
      "source": "NagarikNews",
      "language": "np",
      "source_url": "https://nagariknews.nagariknetwork.com/international/hormuz-free-for-only-60-days-what-s-in-the-14-point-agreement-between-the-us-and-iran-89-44.html?click_from=just_in",
      "image_url": "https://images.nagariknewscdn.com/thumbs/2025/third-party/1781746221_rtump-480x320.jpg"
    },
    {
      "title": "परराष्ट्रमन्त्री स्वदेश फिर्ता, चीन भ्रमण द्विपक्षीय सम्बन्ध थप विस्तारमा फलदायी",
      "summary": "फिफा विश्वकप फुटबल प्रतियोगिताअन्तर्गत सम्पन्न खेलमा उज्वेकिस्तानविरुद्ध कोलोम्बियाले ३-१ को जित निकालेको छ।",
      "source": "NagarikNews",
      "language": "np",
      "source_url": "https://nagariknews.nagariknetwork.com/sports/fifa-world-cup-colombia-beats-uzbekistan-3-1-76-28.html?click_from=just_in",
      "image_url": "https://images.nagariknewscdn.com/thumbs/2025/third-party/1781755876_colambia (2)-480x320.jpg"
    },
    {
      "title": "दिपक र सुलभलाई थुनामा पठाउन आदेश",
      "summary": "राष्ट्रिय प्रजातन्त्र पार्टी (राप्रपा)को केन्द्रीय कार्यसम्पादन समितिको बैठक आज (बिहीबार) बस्दै छ।",
      "source": "NagarikNews",
      "language": "np",
      "source_url": "https://nagariknews.nagariknetwork.com/politics/rpp-s-performance-committee-meeting-underway-85-42.html?click_from=just_in",
      "image_url": ""
    }
  ]
}